ktdg/__init__.py
ktdg/answers.py
ktdg/cli.py
ktdg/distributions.py
ktdg/generation.py
ktdg/py.typed
ktdg/questions.py
ktdg/skills.py
ktdg/students.py
ktdg/utils.py
ktdg-0.1.18.dist-info/LICENSE
ktdg-0.1.18.dist-info/entry_points.txt
ktdg-0.1.18.dist-info/METADATA
ktdg-0.1.18.dist-info/WHEEL
ktdg-0.1.18.dist-info/RECORD
