Metadata-Version: 2.1
Name: ktdg
Version: 0.1.18
Summary: Library to simulate knowledge tracing datasets
Home-page: https://gitlab.com/antoinelb/ktdg
Keywords: knowledge-tracing,research,synthetic-data
Author: Antoine Lefebvre-Brossard
Author-email: antoinelb@protonmail.com
Requires-Python: >=3.10,<4.0
Classifier: Programming Language :: Python :: 3
Classifier: Programming Language :: Python :: 3.10
Classifier: Programming Language :: Python :: 3.11
Requires-Dist: numpy (>=1.23.0,<2.0.0)
Requires-Dist: pydantic (>=1.9.1,<2.0.0)
Requires-Dist: ruamel.yaml (>=0.17.21,<0.18.0)
Requires-Dist: tqdm (>=4.64.0,<5.0.0)
Requires-Dist: typer (>=0.7.0,<0.8.0)
Project-URL: Repository, https://gitlab.com/antoinelb/ktdg
